odoo/addons/ebill_postfinance/README.rst
odoo/addons/ebill_postfinance/__init__.py
odoo/addons/ebill_postfinance/__manifest__.py
odoo/addons/ebill_postfinance/data/ir_cron.xml
odoo/addons/ebill_postfinance/data/mail_activity_type.xml
odoo/addons/ebill_postfinance/data/transmit.method.xml
odoo/addons/ebill_postfinance/i18n/ebill_postfinance.pot
odoo/addons/ebill_postfinance/messages/invoice-2003A.jinja
odoo/addons/ebill_postfinance/messages/invoice-yellowbill.jinja
odoo/addons/ebill_postfinance/messages/ybInvoice_V2.0.4.xsd
odoo/addons/ebill_postfinance/migrations/14.0.1.1.0/pre-migrate.py
odoo/addons/ebill_postfinance/models/__init__.py
odoo/addons/ebill_postfinance/models/account_move.py
odoo/addons/ebill_postfinance/models/ebill_payment_contract.py
odoo/addons/ebill_postfinance/models/ebill_postfinance_invoice_message.py
odoo/addons/ebill_postfinance/models/ebill_postfinance_service.py
odoo/addons/ebill_postfinance/models/sale_order.py
odoo/addons/ebill_postfinance/readme/CONFIGURE.rst
odoo/addons/ebill_postfinance/readme/CONTRIBUTORS.rst
odoo/addons/ebill_postfinance/readme/DESCRIPTION.rst
odoo/addons/ebill_postfinance/readme/INSTALL.rst
odoo/addons/ebill_postfinance/readme/ROADMAP.rst
odoo/addons/ebill_postfinance/readme/USAGE.rst
odoo/addons/ebill_postfinance/security/ir.model.access.csv
odoo/addons/ebill_postfinance/static/description/icon.png
odoo/addons/ebill_postfinance/static/description/index.html
odoo/addons/ebill_postfinance/tests/__init__.py
odoo/addons/ebill_postfinance/tests/common.py
odoo/addons/ebill_postfinance/tests/test_ebill_postfinance.py
odoo/addons/ebill_postfinance/tests/test_ebill_postfinance_message_yb.py
odoo/addons/ebill_postfinance/tests/test_ebill_postfinance_message_yb_creditnote.py
odoo/addons/ebill_postfinance/tests/examples/credit_note_yb.xml
odoo/addons/ebill_postfinance/tests/examples/invoice_qr_yb.xml
odoo/addons/ebill_postfinance/tests/examples/yellowbill_qr_iban.xml
odoo14_addon_ebill_postfinance-14.0.1.1.1.dev4.dist-info/METADATA
odoo14_addon_ebill_postfinance-14.0.1.1.1.dev4.dist-info/WHEEL
odoo14_addon_ebill_postfinance-14.0.1.1.1.dev4.dist-info/top_level.txt
odoo14_addon_ebill_postfinance-14.0.1.1.1.dev4.dist-info/RECORD
