Metadata-Version: 2.1
Name: odoo14-addon-ebill_postfinance
Version: 14.0.1.1.1.dev4
Summary: Postfinance eBill integration
Home-page: https://github.com/OCA/l10n-switzerland
Author: Camptocamp,Odoo Community Association (OCA)
Author-email: support@odoo-community.org
License: AGPL-3
Classifier: Programming Language :: Python
Classifier: Framework :: Odoo
Classifier: Framework :: Odoo :: 14.0
Classifier: License :: OSI Approved :: GNU Affero General Public License v3
Requires-Python: >=3.6
Requires-Dist: ebilling-postfinance
Requires-Dist: odoo14-addon-account-invoice-export
Requires-Dist: odoo14-addon-base-ebill-payment-contract
Requires-Dist: odoo14-addon-l10n-ch-base-bank
Requires-Dist: odoo14-addon-queue-job
Requires-Dist: odoo<14.1dev,>=14.0a
Requires-Dist: zeep
